neofetch/__init__.py
neofetch/main.py
neofetch_python-0.2.0.dist-info/LICENSE
neofetch_python-0.2.0.dist-info/METADATA
neofetch_python-0.2.0.dist-info/WHEEL
neofetch_python-0.2.0.dist-info/entry_points.txt
neofetch_python-0.2.0.dist-info/top_level.txt
neofetch_python-0.2.0.dist-info/RECORD
