Metadata-Version: 2.1
Name: neofetch-python
Version: 0.2.0
Summary: A Python implementation of neofetch
Author: Your Name
Author-email: firi8228@gmail.com
Classifier: Programming Language :: Python :: 3
Classifier: License :: OSI Approved :: MIT License
Classifier: Operating System :: OS Independent
Requires-Python: >=3.6
License-File: LICENSE
Requires-Dist: psutil
Requires-Dist: colorama
Requires-Dist: wmi
